service_file_to_text/__init__.py
service_file_to_text/fast_api/File_To_Text__Fast_API.py
service_file_to_text/fast_api/__init__.py
service_file_to_text/fast_api/routes/Routes__Info.py
service_file_to_text/fast_api/routes/__init__.py
service_file_to_text/lambdas/__init__.py
service_file_to_text/lambdas/handler.py
service_file_to_text/markitdown/Markitdown_Service.py
service_file_to_text/markitdown/routes/Routes__Markitdown.py
service_file_to_text/markitdown/sample_files/sample.pdf
service_file_to_text/markitdown/sample_files/test.jpg
service_file_to_text/markitdown/sample_files/test.xlsx
service_file_to_text/testing/__init__.py
service_file_to_text/testing/file_to_text__objs_for_tests.py
service_file_to_text/utils/Version.py
service_file_to_text/utils/__init__.py
service_file_to_text/version
service_file_to_text-0.2.0.dist-info/LICENSE
service_file_to_text-0.2.0.dist-info/METADATA
service_file_to_text-0.2.0.dist-info/WHEEL
service_file_to_text-0.2.0.dist-info/RECORD
