Metadata-Version: 2.1
Name: service_file_to_text
Version: 0.2.0
Summary: Service - File to Text
Home-page: https://github.com/the-cyber-boardroom/service--file-to-text
License: Apache 2.0
Author: Dinis Cruz
Author-email: dinis.cruz@owasp.org
Requires-Python: >=3.11,<4.0
Classifier: License :: Other/Proprietary License
Classifier: Programming Language :: Python :: 3
Classifier: Programming Language :: Python :: 3.11
Classifier: Programming Language :: Python :: 3.12
Classifier: Programming Language :: Python :: 3.13
Requires-Dist: bs4
Requires-Dist: httpx
Requires-Dist: mangum
Requires-Dist: markitdown
Requires-Dist: osbot-aws
Requires-Dist: osbot-fast-api
Requires-Dist: osbot-utils
Requires-Dist: pillow
Requires-Dist: pytesseract
Requires-Dist: python-multipart
Requires-Dist: uvicorn
Project-URL: Repository, https://github.com/the-cyber-boardroom/service--file-to-text
